get_certificate_chain/download.py
get_certificate_chain/tests/__init__.py
get_certificate_chain/tests/test_cert.py
get_certificate_chain/tests/test_data/generate_cert.sh
get_certificate_chain/tests/test_data/root_ca.cnf
get_certificate_chain/tests/test_data/server.cnf
get_certificate_chain-0.1.8.dist-info/LICENSE.md
get_certificate_chain-0.1.8.dist-info/METADATA
get_certificate_chain-0.1.8.dist-info/WHEEL
get_certificate_chain-0.1.8.dist-info/entry_points.txt
get_certificate_chain-0.1.8.dist-info/RECORD
