Metadata-Version: 2.1
Name: get-certificate-chain
Version: 0.1.8
Summary: Project to help use the breadcrumbs that are left by the certificate to build the chain and output it into files.
License: MIT
Author: Calvin Remsburg
Author-email: cremsburg.dev@gmail.com
Requires-Python: >=3.9,<4.0
Classifier: License :: OSI Approved :: MIT License
Classifier: Programming Language :: Python :: 3
Classifier: Programming Language :: Python :: 3.9
Classifier: Programming Language :: Python :: 3.10
Classifier: Programming Language :: Python :: 3.11
Requires-Dist: argparse (>=1.4.0,<2.0.0)
Requires-Dist: cryptography (>=40.0.1,<41.0.0)
Requires-Dist: pytest (>=7.3.1,<8.0.0)
